Metadata-Version: 2.1
Name: yalice
Version: 0.1
Summary: Python library for writing applications on yandex voice assistant
Home-page: https://github.com/cutefluffyfox/pyalice
Author: cutefluffyfox
Author-email: mishkazel1@mail.ru
License: UNKNOWN
Platform: UNKNOWN
Classifier: Programming Language :: Python :: 3
Classifier: License :: OSI Approved :: MIT License
Classifier: Operating System :: OS Independent
Requires-Python: >=3.6
